inteligenciartificial/__init__.py
inteligenciartificial/modelografosprobabilisticos/__init__.py
inteligenciartificial/modelografosprobabilisticos/grafo.py
inteligenciartificial/modelografosprobabilisticos/utils.py
inteligenciartificial/modelografosprobabilisticos/busqueda/__init__.py
inteligenciartificial/modelografosprobabilisticos/busqueda/k2.py
inteligenciartificial/modelografosprobabilisticos/distribuciones/__init__.py
inteligenciartificial/modelografosprobabilisticos/distribuciones/discreta.py
inteligenciartificial/modelografosprobabilisticos/metricas/__init__.py
inteligenciartificial/modelografosprobabilisticos/metricas/bic.py
inteligenciartificial/modelografosprobabilisticos/metricas/entropia.py
inteligenciartificial/modelografosprobabilisticos/modelos/__init__.py
inteligenciartificial/modelografosprobabilisticos/modelos/naive_bayes.py
inteligenciartificial/modelografosprobabilisticos/modelos/red_bayesiana.py
inteligenciartificial-0.0.3.dist-info/METADATA
inteligenciartificial-0.0.3.dist-info/WHEEL
inteligenciartificial-0.0.3.dist-info/top_level.txt
inteligenciartificial-0.0.3.dist-info/RECORD
